versionhq/__init__.py
versionhq/_prompt/auto_feedback.py
versionhq/_prompt/constants.py
versionhq/_prompt/model.py
versionhq/_utils/__init__.py
versionhq/_utils/convert_img_url.py
versionhq/_utils/handle_directory.py
versionhq/_utils/i18n.py
versionhq/_utils/is_valid_enum.py
versionhq/_utils/is_valid_url.py
versionhq/_utils/llm_as_a_judge.py
versionhq/_utils/logger.py
versionhq/_utils/process_config.py
versionhq/_utils/usage_metrics.py
versionhq/_utils/vars.py
versionhq/agent/__init__.py
versionhq/agent/inhouse_agents.py
versionhq/agent/model.py
versionhq/agent/parser.py
versionhq/agent/rpm_controller.py
versionhq/agent/TEMPLATES/Backstory.py
versionhq/agent/TEMPLATES/__init__.py
versionhq/agent_network/__init__.py
versionhq/agent_network/formation.py
versionhq/agent_network/model.py
versionhq/cli/__init__.py
versionhq/clients/__init__.py
versionhq/clients/customer/__init__.py
versionhq/clients/customer/model.py
versionhq/clients/product/__init__.py
versionhq/clients/product/model.py
versionhq/clients/workflow/__init__.py
versionhq/clients/workflow/model.py
versionhq/knowledge/__init__.py
versionhq/knowledge/_utils.py
versionhq/knowledge/embedding.py
versionhq/knowledge/model.py
versionhq/knowledge/source.py
versionhq/knowledge/source_docling.py
versionhq/knowledge/storage.py
versionhq/llm/__init__.py
versionhq/llm/llm_vars.py
versionhq/llm/model.py
versionhq/memory/__init__.py
versionhq/memory/contextual_memory.py
versionhq/memory/model.py
versionhq/storage/__init__.py
versionhq/storage/base.py
versionhq/storage/ltm_sqlite_storage.py
versionhq/storage/mem0_storage.py
versionhq/storage/rag_storage.py
versionhq/storage/task_output_storage.py
versionhq/storage/utils.py
versionhq/task/__init__.py
versionhq/task/evaluation.py
versionhq/task/formatter.py
versionhq/task/model.py
versionhq/task/structured_response.py
versionhq/task/TEMPLATES/Description.py
versionhq/task_graph/__init__.py
versionhq/task_graph/colors.py
versionhq/task_graph/draft.py
versionhq-1.2.4.19.dist-info/licenses/LICENSE
versionhq-1.2.4.19.dist-info/METADATA
versionhq-1.2.4.19.dist-info/WHEEL
versionhq-1.2.4.19.dist-info/top_level.txt
versionhq-1.2.4.19.dist-info/RECORD
