Metadata-Version: 2.4
Name: versionhq
Version: 1.2.4.19
Summary: Autonomous agent networks for task automation with multi-step reasoning.
Author-email: Kuriko Iwai <krik8235@gmail.com>
License: MIT License
Project-URL: Homepage, https://versionhq.vercel.app
Project-URL: Documentation, https://versionhq.github.io/multi-agent-system
Project-URL: Repository, https://github.com/versionHQ/multi-agent-system
Project-URL: Issues, https://github.com/versionHQ/multi-agent-system/issues
Keywords: autonomic agent networks,deep agent,agentic orchestration framework
Classifier: Programming Language :: Python
Classifier: Programming Language :: Python :: 3
Classifier: Programming Language :: Python :: 3.11
Classifier: Programming Language :: Python :: 3.12
Classifier: Programming Language :: Python :: 3.13
Classifier: License :: OSI Approved :: MIT License
Classifier: Operating System :: OS Independent
Classifier: Development Status :: 3 - Alpha
Classifier: Intended Audience :: Developers
Classifier: Intended Audience :: Information Technology
Classifier: Topic :: Software Development :: Build Tools
Requires-Python: >=3.11
License-File: LICENSE
Requires-Dist: regex==2024.11.6
Requires-Dist: pydantic>=2.10.6
Requires-Dist: typing>=0.0.0
Requires-Dist: json-repair>=0.0.0
Requires-Dist: litellm>=1.55.8
Requires-Dist: composio>=0.1.0
Requires-Dist: setuptools>=75.6.0
Requires-Dist: wheel>=0.45.1
Requires-Dist: python-dotenv>=1.0.0
Requires-Dist: appdirs>=1.4.4
Requires-Dist: langchain>=0.3.14
Requires-Dist: langchain-openai>=0.2.14
Requires-Dist: chromadb>=0.6.3
Requires-Dist: wheel>=0.45.1
Requires-Dist: composio-core==0.7.0
Requires-Dist: networkx>=3.4.2
Requires-Dist: matplotlib>=3.10.0
Requires-Dist: boto3>=1.37.1
Requires-Dist: scikit-learn>=1.6.1
Requires-Dist: numpy>=1.26.4
Requires-Dist: pandas>=2.2.3
Provides-Extra: docling
Requires-Dist: docling>=2.25.2; extra == "docling"
Provides-Extra: mem0ai
Requires-Dist: mem0ai>=0.1.55; extra == "mem0ai"
Provides-Extra: pdfplumber
Requires-Dist: pdfplumber>=0.11.5; extra == "pdfplumber"
Provides-Extra: pygraphviz
Requires-Dist: pygraphviz>=1.14; extra == "pygraphviz"
Provides-Extra: tools
Requires-Dist: html2text>=2024.2.26; extra == "tools"
Requires-Dist: sec-api>=1.0.28; extra == "tools"
Requires-Dist: pytest-playwright>=0.7.0; extra == "tools"
Requires-Dist: selenium>=4.30.0; extra == "tools"
Provides-Extra: torch
Requires-Dist: torch>=2.6.0; extra == "torch"
Requires-Dist: torchvision>=0.21.0; extra == "torch"
Dynamic: license-file
